playwright_captcha/__init__.py
playwright_captcha/captchas/__init__.py
playwright_captcha/captchas/cloudflare_interstitial/__init__.py
playwright_captcha/captchas/cloudflare_interstitial/apply.py
playwright_captcha/captchas/cloudflare_interstitial/detect_data.py
playwright_captcha/captchas/cloudflare_interstitial/solvers/__init__.py
playwright_captcha/captchas/cloudflare_interstitial/solvers/click.py
playwright_captcha/captchas/cloudflare_interstitial/solvers/twocaptcha.py
playwright_captcha/captchas/cloudflare_turnstile/__init__.py
playwright_captcha/captchas/cloudflare_turnstile/apply.py
playwright_captcha/captchas/cloudflare_turnstile/detect_data.py
playwright_captcha/captchas/cloudflare_turnstile/solvers/__init__.py
playwright_captcha/captchas/cloudflare_turnstile/solvers/click.py
playwright_captcha/captchas/cloudflare_turnstile/solvers/twocaptcha.py
playwright_captcha/captchas/recaptcha_v2/__init__.py
playwright_captcha/captchas/recaptcha_v2/apply.py
playwright_captcha/captchas/recaptcha_v2/detect_data.py
playwright_captcha/captchas/recaptcha_v2/solvers/__init__.py
playwright_captcha/captchas/recaptcha_v2/solvers/twocaptcha.py
playwright_captcha/captchas/recaptcha_v3/__init__.py
playwright_captcha/captchas/recaptcha_v3/apply.py
playwright_captcha/captchas/recaptcha_v3/detect_data.py
playwright_captcha/captchas/recaptcha_v3/solvers/__init__.py
playwright_captcha/captchas/recaptcha_v3/solvers/twocaptcha.py
playwright_captcha/solvers/__init__.py
playwright_captcha/solvers/base_solver.py
playwright_captcha/solvers/api/__init__.py
playwright_captcha/solvers/api/api_solver_base.py
playwright_captcha/solvers/api/twocaptcha/__init__.py
playwright_captcha/solvers/api/twocaptcha/twocaptcha_solver.py
playwright_captcha/solvers/click/__init__.py
playwright_captcha/solvers/click/click_solver.py
playwright_captcha/solvers/click/cloudflare/__init__.py
playwright_captcha/solvers/click/cloudflare/solve_by_click.py
playwright_captcha/solvers/click/cloudflare/utils/__init__.py
playwright_captcha-0.1.1.dist-info/licenses/LICENSE
playwright_captcha-0.1.1.dist-info/METADATA
playwright_captcha-0.1.1.dist-info/WHEEL
playwright_captcha-0.1.1.dist-info/top_level.txt
playwright_captcha-0.1.1.dist-info/RECORD
